MPSPEnv/__init__.py
MPSPEnv/c_interface.py
MPSPEnv/c_lib.cpython-311-darwin.so
MPSPEnv/env.py
MPSPEnv/visualizer.py
MPSPEnv-0.1.5.dist-info/METADATA
MPSPEnv-0.1.5.dist-info/WHEEL
MPSPEnv-0.1.5.dist-info/top_level.txt
MPSPEnv-0.1.5.dist-info/RECORD
