Metadata-Version: 2.1
Name: MPSPEnv
Version: 0.1.5
Summary: A reinforcement learning environment for the Multi Port Stowage Planning problem
Author: Axel Højmark
Author-email: axelhojmark@gmail.com
Project-URL: Repository, https://github.com/hojmax/MPSPEnv
Requires-Dist: pygame
Requires-Dist: gymnasium
Requires-Dist: numpy
Requires-Dist: seaborn
